duowen_huqie/__init__.py
duowen_huqie/new_word_detection/__init__.py
duowen_huqie/new_word_detection/model.py
duowen_huqie/new_word_detection/utils.py
duowen_huqie/nlp/__init__.py
duowen_huqie/nlp/query.py
duowen_huqie/nlp/rag_tokenizer.py
duowen_huqie/nlp/re_pattern.py
duowen_huqie/nlp/stopwords.py
duowen_huqie/nlp/synonym.py
duowen_huqie/nlp/term_weight.py
duowen_huqie/nlp/utils.py
duowen_huqie/res/huqie.txt
duowen_huqie/res/ner.json
duowen_huqie/res/synonym.json
duowen_huqie/utils.py
duowen_huqie-0.1.11.dist-info/METADATA
duowen_huqie-0.1.11.dist-info/WHEEL
duowen_huqie-0.1.11.dist-info/RECORD
