Metadata-Version: 2.1
Name: duowen-huqie
Version: 0.1.11
Summary: 
Author: liurui
Author-email: liurui@asiainfo.com
Requires-Python: >=3.10,<4
Classifier: Programming Language :: Python :: 3
Classifier: Programming Language :: Python :: 3.10
Classifier: Programming Language :: Python :: 3.11
Classifier: Programming Language :: Python :: 3.12
Requires-Dist: chardet (>=5.2.0,<6.0.0)
Requires-Dist: datrie (>=0.8.2,<0.9.0)
Requires-Dist: hanziconv (>=0.3.2,<0.4.0)
Requires-Dist: nltk (>=3.9.1,<4.0.0)
Requires-Dist: numpy (>=1.23)
